epm_client/__init__.py
epm_client/api_client.py
epm_client/configuration.py
epm_client/rest.py
epm_client/apis/__init__.py
epm_client/apis/adapter_api.py
epm_client/apis/cluster_api.py
epm_client/apis/key_api.py
epm_client/apis/network_api.py
epm_client/apis/package_api.py
epm_client/apis/po_p_api.py
epm_client/apis/resource_group_api.py
epm_client/apis/runtime_api.py
epm_client/apis/tosca_api.py
epm_client/apis/vdu_api.py
epm_client/apis/worker_api.py
epm_client/models/__init__.py
epm_client/models/adapter.py
epm_client/models/auth_credentials.py
epm_client/models/cluster.py
epm_client/models/cluster_from_resource_group.py
epm_client/models/command_execution_body.py
epm_client/models/event.py
epm_client/models/file_download_body.py
epm_client/models/file_upload_body.py
epm_client/models/key.py
epm_client/models/key_value_pair.py
epm_client/models/network.py
epm_client/models/po_p.py
epm_client/models/resource_group.py
epm_client/models/vdu.py
epm_client/models/worker.py
epm_client/models/worker_from_vdu.py
epm_client-1.0.0.dist-info/DESCRIPTION.rst
epm_client-1.0.0.dist-info/METADATA
epm_client-1.0.0.dist-info/RECORD
epm_client-1.0.0.dist-info/WHEEL
epm_client-1.0.0.dist-info/metadata.json
epm_client-1.0.0.dist-info/top_level.txt
test/other_tests/__init__.py
test/other_tests/test_command_execution_body.py
test/other_tests/test_event.py
test/other_tests/test_file_download_body.py
test/other_tests/test_file_upload_body.py
test/other_tests/test_key_value_pair.py
test/other_tests/test_network.py
test/other_tests/test_po_p.py
test/other_tests/test_resource_group.py
test/other_tests/test_vdu.py
