Metadata-Version: 2.0
Name: epm-client
Version: 1.0.0
Summary: EPM REST API
Home-page: https://github.com/tub-elastest/epm-client-python
Author: UNKNOWN
Author-email: michael.pauls@tu-berlin.de
License: UNKNOWN
Keywords: Swagger,Python,EPM REST Client
Platform: UNKNOWN
